py3_downloader/__init__.py
py3_downloader/downloader.py
py3_downloader-0.0.3.dist-info/METADATA
py3_downloader-0.0.3.dist-info/WHEEL
py3_downloader-0.0.3.dist-info/licenses/LICENSE
py3_downloader-0.0.3.dist-info/RECORD
