Metadata-Version: 2.4
Name: py3-downloader
Version: 0.0.3
Summary: python3 downloader
License-File: LICENSE
Author: mathewgeola
Author-email: mathewgeola@gmail.com
Requires-Python: >=3.12
Classifier: Programming Language :: Python :: 3
Classifier: Programming Language :: Python :: 3.12
Classifier: Programming Language :: Python :: 3.13
Classifier: Programming Language :: Python :: 3.14
Requires-Dist: py3-web (>=0.0.7,<0.0.8)
Requires-Dist: tqdm (>=4.67.1,<5.0.0)
